werkzeug-stubs/METADATA.toml
werkzeug-stubs/__init__.pyi
werkzeug-stubs/_compat.pyi
werkzeug-stubs/_internal.pyi
werkzeug-stubs/_reloader.pyi
werkzeug-stubs/datastructures.pyi
werkzeug-stubs/exceptions.pyi
werkzeug-stubs/filesystem.pyi
werkzeug-stubs/formparser.pyi
werkzeug-stubs/http.pyi
werkzeug-stubs/local.pyi
werkzeug-stubs/posixemulation.pyi
werkzeug-stubs/routing.pyi
werkzeug-stubs/script.pyi
werkzeug-stubs/security.pyi
werkzeug-stubs/serving.pyi
werkzeug-stubs/test.pyi
werkzeug-stubs/testapp.pyi
werkzeug-stubs/urls.pyi
werkzeug-stubs/useragents.pyi
werkzeug-stubs/utils.pyi
werkzeug-stubs/wrappers.pyi
werkzeug-stubs/wsgi.pyi
werkzeug-stubs/contrib/__init__.pyi
werkzeug-stubs/contrib/atom.pyi
werkzeug-stubs/contrib/cache.pyi
werkzeug-stubs/contrib/fixers.pyi
werkzeug-stubs/contrib/iterio.pyi
werkzeug-stubs/contrib/jsrouting.pyi
werkzeug-stubs/contrib/limiter.pyi
werkzeug-stubs/contrib/lint.pyi
werkzeug-stubs/contrib/profiler.pyi
werkzeug-stubs/contrib/securecookie.pyi
werkzeug-stubs/contrib/sessions.pyi
werkzeug-stubs/contrib/testtools.pyi
werkzeug-stubs/contrib/wrappers.pyi
werkzeug-stubs/debug/__init__.pyi
werkzeug-stubs/debug/console.pyi
werkzeug-stubs/debug/repr.pyi
werkzeug-stubs/debug/tbtools.pyi
werkzeug-stubs/middleware/__init__.pyi
werkzeug-stubs/middleware/dispatcher.pyi
werkzeug-stubs/middleware/http_proxy.pyi
werkzeug-stubs/middleware/lint.pyi
werkzeug-stubs/middleware/profiler.pyi
werkzeug-stubs/middleware/proxy_fix.pyi
werkzeug-stubs/middleware/shared_data.pyi
types_Werkzeug-1.0.8.dist-info/METADATA
types_Werkzeug-1.0.8.dist-info/WHEEL
types_Werkzeug-1.0.8.dist-info/top_level.txt
types_Werkzeug-1.0.8.dist-info/RECORD
