Metadata-Version: 2.1
Name: types-Werkzeug
Version: 1.0.8
Summary: Typing stubs for Werkzeug
Home-page: https://github.com/python/typeshed
License: Apache-2.0 license
Platform: UNKNOWN
Classifier: License :: OSI Approved :: Apache Software License
Classifier: Typing :: Typed
